pydirac_papertools/__init__.py
pydirac_papertools/constant.py
pydirac_papertools/figure.py
pydirac_papertools/formula.py
pydirac_papertools/table.py
pydirac_papertools/data/__init__.py
pydirac_papertools/data/atom_dipole_footer.tex
pydirac_papertools/data/atom_dipole_header.tex
pydirac_papertools/data/best_solutions.json
pydirac_papertools/data/best_solutions_with_DC-CI.json
pydirac_papertools/data/group_dipole_footer.tex
pydirac_papertools/data/group_dipole_header.tex
pydirac_papertools/data/mrci_group_13_body.tex
pydirac_papertools/data/mrci_group_14_body.tex
pydirac_papertools/data/mrci_group_15_body.tex
pydirac_papertools/data/mrci_group_16_body.tex
pydirac_papertools/data/mrci_group_17_body.tex
pydirac_papertools/data/mrci_group_1_11_body.tex
pydirac_papertools/data/mrci_group_2_12_18_body.tex
pydirac_papertools/data/plot_style.txt
pydirac_papertools/data/plot_style_long_fig.txt
pydirac_papertools/data/socc_dipole_body.tex
pydirac_papertools/data/socc_dipole_ccsd_body.tex
pydirac_papertools/data/socc_quad_ccsd_body.tex
pydirac_papertools/data/srcc_dipole_body.tex
pydirac_papertools/data/srcc_dipole_ml0_body.tex
pydirac_papertools/data/srcc_quad_body.tex
pydirac_papertools/data/srcc_quad_ml0_body.tex
pydirac_papertools/processor/__init__.py
pydirac_papertools/processor/abstract.py
pydirac_papertools/processor/atom.py
pydirac_papertools/processor/group.py
pydirac_papertools/processor/utils.py
pydirac_papertools/processor/methods/__init__.py
pydirac_papertools/processor/methods/dccc.py
pydirac_papertools/processor/methods/dcci.py
pydirac_papertools/processor/methods/nrcc.py
pydirac_papertools/processor/methods/srcc.py
pydirac_papertools/scripts/__init__.py
pydirac_papertools/scripts/write_best_solution.py
pydirac_papertools-2024.7.8.dist-info/LICENSE
pydirac_papertools-2024.7.8.dist-info/METADATA
pydirac_papertools-2024.7.8.dist-info/WHEEL
pydirac_papertools-2024.7.8.dist-info/entry_points.txt
pydirac_papertools-2024.7.8.dist-info/top_level.txt
pydirac_papertools-2024.7.8.dist-info/RECORD
