Metadata-Version: 2.1
Name: pydirac-papertools
Version: 2024.7.8
Summary: Tools for writting database of dipole polarizability
Author-email: YingXing Cheng <yxcheng2buaa@gmail.com>
License: GNU GENERAL PUBLIC LICENSE
Project-URL: Issues, https://github.com/yingxingcheng/pydirac-papertools/issues
Project-URL: Source, https://github.com/yingxingcheng/pydirac-papertools/
Project-URL: Changelog, https://github.com/yingxingcheng/pydirac-papertools/blob/main/CHANGELOG.md
Classifier: Development Status :: 3 - Alpha
Classifier: Environment :: Console
Classifier: Intended Audience :: Science/Research
Classifier: Intended Audience :: Education
Classifier: Framework :: Matplotlib
Classifier: License :: OSI Approved :: GNU General Public License v3 or later (GPLv3+)
Classifier: Natural Language :: English
Classifier: Operating System :: POSIX
Classifier: Operating System :: MacOS
Classifier: Programming Language :: Python :: 3
Classifier: Topic :: Scientific/Engineering
Classifier: Topic :: Text Processing
Requires-Python: >=3.6
License-File: LICENSE
Requires-Dist: numpy
Requires-Dist: matplotlib
Requires-Dist: pandas
Requires-Dist: importlib-resources
Requires-Dist: pydirac ==2024.7.8
Provides-Extra: dev
Requires-Dist: pre-commit ; extra == 'dev'
Provides-Extra: tests
Requires-Dist: pytest ; extra == 'tests'
